Metadata-Version: 2.4
Name: llama-index-readers-assemblyai
Version: 0.4.1
Summary: llama-index readers assemblyai integration
Author-email: Your Name <you@example.com>
Maintainer: patrickloeber
License-Expression: MIT
License-File: LICENSE
Requires-Python: <4.0,>=3.9
Requires-Dist: assemblyai>=0.18.0
Requires-Dist: llama-index-core<0.15,>=0.13.0
